dictat/__init__.py
dictat/py.typed
dictat-1.2.0.dist-info/METADATA
dictat-1.2.0.dist-info/UNLICENSE
dictat-1.2.0.dist-info/WHEEL
dictat-1.2.0.dist-info/top_level.txt
dictat-1.2.0.dist-info/RECORD
