Metadata-Version: 2.1
Name: dictat
Version: 1.2.0
Summary: Adict is an attribute-accessible dynamic dictionary wrapper
Home-page: https://gitlab.com/janoskut/dictat
Author: Janos Kutscherauer
Author-email: janoskut@gmail.com
License: UNLICENSE
Requires-Python: >=3.7
License-File: UNLICENSE
